bullet.py
enemy.py
main.py
player.py
space_invaders_pygame-1.0.0.dist-info/METADATA
space_invaders_pygame-1.0.0.dist-info/WHEEL
space_invaders_pygame-1.0.0.dist-info/entry_points.txt
space_invaders_pygame-1.0.0.dist-info/top_level.txt
space_invaders_pygame-1.0.0.dist-info/RECORD
