Metadata-Version: 2.4
Name: space-invaders-pygame
Version: 1.0.0
Summary: A simple Space Invaders-style arcade game built with Pygame.
Author: Your Name
Requires-Python: >=3.7
Requires-Dist: pygame>=2.0.0
Dynamic: author
Dynamic: requires-dist
Dynamic: requires-python
Dynamic: summary
